libcellml/__init__.py
libcellml/_analyser.so
libcellml/_analyserequation.so
libcellml/_analyserequationast.so
libcellml/_analysermodel.so
libcellml/_analyservariable.so
libcellml/_annotator.so
libcellml/_component.so
libcellml/_componententity.so
libcellml/_entity.so
libcellml/_enums.so
libcellml/_generator.so
libcellml/_generatorprofile.so
libcellml/_importedentity.so
libcellml/_importer.so
libcellml/_importsource.so
libcellml/_issue.so
libcellml/_logger.so
libcellml/_model.so
libcellml/_namedentity.so
libcellml/_parser.so
libcellml/_printer.so
libcellml/_reset.so
libcellml/_types.so
libcellml/_units.so
libcellml/_validator.so
libcellml/_variable.so
libcellml/_version.so
libcellml/analyser.py
libcellml/analyserequation.py
libcellml/analyserequationast.py
libcellml/analysermodel.py
libcellml/analyservariable.py
libcellml/annotator.py
libcellml/component.py
libcellml/componententity.py
libcellml/entity.py
libcellml/enums.py
libcellml/generator.py
libcellml/generatorprofile.py
libcellml/importedentity.py
libcellml/importer.py
libcellml/importsource.py
libcellml/issue.py
libcellml/libcellml.0.3.0-rc.171.dylib
libcellml/logger.py
libcellml/model.py
libcellml/namedentity.py
libcellml/parser.py
libcellml/printer.py
libcellml/reset.py
libcellml/types.py
libcellml/units.py
libcellml/validator.py
libcellml/variable.py
libcellml/version.py
l1bcellml-0.3.0rc171.dist-info/METADATA
l1bcellml-0.3.0rc171.dist-info/WHEEL
l1bcellml-0.3.0rc171.dist-info/top_level.txt
l1bcellml-0.3.0rc171.dist-info/RECORD
