Metadata-Version: 2.1
Name: l1bcellml
Version: 0.3.0rc171
Summary: libCellML Library: A library for the parsing, printing, and manipulation
Home-page: https://libcellml.org
Author: libCellML developers
Author-email: libcellml@googlegroups.com
License: Apache Software License
Platform: UNKNOWN
Classifier: Development Status :: 5 - Production/Stable
Classifier: Intended Audience :: Developers
Classifier: Intended Audience :: Education
Classifier: Intended Audience :: Science/Research
Classifier: License :: OSI Approved :: Apache Software License
Classifier: Programming Language :: Python
Classifier: Operating System :: Microsoft :: Windows
Classifier: Operating System :: Unix
Classifier: Operating System :: MacOS :: MacOS X
Classifier: Topic :: Software Development :: Libraries :: Python Modules
Classifier: 
